LICENSE
dublincore_resource/__init__.py
dublincore_resource/admin.py
dublincore_resource/apps.py
dublincore_resource/migrations/0001_initial.py
dublincore_resource/migrations/0002_auto_20191211_0113.py
dublincore_resource/migrations/0003_auto_20191211_1449.py
dublincore_resource/migrations/0004_auto_20191211_1917.py
dublincore_resource/migrations/0005_auto_20200727_1227.py
dublincore_resource/migrations/__init__.py
dublincore_resource/models.py
dublincore_resource/settings.py
dublincore_resource/tests.py
dublincore_resource/views.py
django_dublincore_resource-0.1.4.dist-info/LICENSE
django_dublincore_resource-0.1.4.dist-info/WHEEL
django_dublincore_resource-0.1.4.dist-info/METADATA
django_dublincore_resource-0.1.4.dist-info/RECORD
