Metadata-Version: 2.1
Name: django-dublincore-resource
Version: 0.1.4
Summary: Describe your resources with a Dublin Core schema
Home-page: https://github.com/kingsdigitallab/django-dublincore-resource
License: MIT
Keywords: dublin-core,controlled-vocabulary,linked-data,vocabulary,metadata
Author: geoffroy-noel-ddh
Author-email: geoffroy.noel@kcl.ac.uk
Requires-Python: >=3.5,<4.0
Classifier: Environment :: Web Environment
Classifier: Framework :: Django :: 2.2
Classifier: License :: OSI Approved :: MIT License
Classifier: Operating System :: OS Independent
Classifier: Programming Language :: Python :: 3
Classifier: Programming Language :: Python :: 3.5
Classifier: Programming Language :: Python :: 3.6
Classifier: Programming Language :: Python :: 3.7
Classifier: Programming Language :: Python :: 3.8
Requires-Dist: django (>=2.2,<3.0)
Requires-Dist: django-controlled-vocabulary (<2)
Project-URL: Repository, https://github.com/kingsdigitallab/django-dublincore-resource
